flojoy_cloud/__init__.py
flojoy_cloud/client.py
flojoy_cloud/dtypes.py
flojoy_cloud/measurement.py
flojoy_cloud/test_sequencer.py
flojoy_cloud/watch.py
flojoy_cloud-0.2.2.dist-info/METADATA
flojoy_cloud-0.2.2.dist-info/WHEEL
flojoy_cloud-0.2.2.dist-info/RECORD
